iso20275/Cleaned - ISO-20275 - 2017-11-30.csv
iso20275/Cleaned - ISO-20275 - 2019-11-06.csv
iso20275/Cleaned - ISO-20275 - 2020-06-10.csv
iso20275/Cleaned - ISO-20275 - 2020-11-19.csv
iso20275/Cleaned - ISO-20275 - 2021-09-23.csv
iso20275/Cleaned - ISO-20275 - 2023-09-28.csv
iso20275/Cleaned - with additional - ISO-20275 - 2019-11-06.csv
iso20275/Cleaned - with additional - ISO-20275 - 2020-11-19.csv
iso20275/Cleaned - with additional - ISO-20275 - 2021-09-23.csv
iso20275/Cleaned - with additional - ISO-20275 - 2023-09-28.csv
iso20275/ISO-20275 - 2017-11-30.csv
iso20275/ISO-20275 - 2019-11-06.csv
iso20275/ISO-20275 - 2020-06-10.csv
iso20275/ISO-20275 - 2020-11-19.csv
iso20275/ISO-20275 - 2021-09-23.csv
iso20275/ISO-20275 - 2023-09-28.csv
iso20275/__init__.py
tests/__init__.py
tests/test_iso20275.py
iso_20275-0.0.18.dist-info/LICENSE
iso_20275-0.0.18.dist-info/METADATA
iso_20275-0.0.18.dist-info/WHEEL
iso_20275-0.0.18.dist-info/top_level.txt
iso_20275-0.0.18.dist-info/RECORD
