Metadata-Version: 2.1
Name: iso-20275
Version: 0.0.18
Summary: ISO 20275 Entity Legal Type package for Python
Home-page: https://github.com/Gawaboumga/iso-20275-python
Author: Youri Hubaut
License: MIT
Keywords: internationalization i18n elf iso20275 entity legal types
Classifier: Development Status :: 1 - Planning
Classifier: Intended Audience :: Developers
Classifier: License :: OSI Approved :: MIT License
Classifier: Operating System :: OS Independent
Classifier: Programming Language :: Python :: 3.6
Classifier: Programming Language :: Python :: 3.7
Classifier: Programming Language :: Python :: 3.8
Classifier: Programming Language :: Python :: 3.9
Classifier: Programming Language :: Python :: 3.10
Classifier: Programming Language :: Python :: 3.11
Classifier: Programming Language :: Python :: 3.12
Classifier: Programming Language :: Python :: Implementation :: CPython
Classifier: Programming Language :: Python :: Implementation :: PyPy
Classifier: Programming Language :: Python :: Implementation :: Stackless
Classifier: Topic :: Software Development :: Internationalization
License-File: LICENSE
Requires-Dist: setuptools
